Workbook

Sheet Forecast
B2: ="Income Statement of "&Cover!F6 -> Income Statement of FinPractice
D3: 2023 | E3: =D3+1 -> 2024 | F3: =E3+1 -> 2025 | G3: =F3+1 -> 2026 | H3: =G3+1 -> 2027 | I3: =H3+1 -> 2028 | J3: =I3+1 -> 2029 | K3: =J3+1 -> 2030
B4: Revenue | D4: 5210 | E4: 5435 | F4: 5710 | G4: =F4*(1+G17) -> 5806.4538 | H4: =G4*(1+H27) -> 6078.7305 | I4: =H4*(1+I27) -> 6363.7748 | J4: =I4*(1+J27) -> 6662.1854 | K4: =J4*(1+K27) -> 6974.5891
B5: Cost of goods sold | D5: 3345 | E5: 3350 | F5: 3551 | G5: =G18*G4 -> 3639.2942 | H5: =H18*H4 -> 3809.9483 | I5: =I18*I4 -> 3988.6047 | J5: =J18*J4 -> 4175.6386 | K5: =K18*K4 -> 4371.443
B6: Gross Profit | D6: 1865 | E6: 2085 | F6: 2159 | G6: =G4-G5 -> 2167.1596 | H6: =H4-H5 -> 2268.7822 | I6: =I4-I5 -> 2375.1701 | J6: =J4-J5 -> 2486.5467 | K6: =K4-K5 -> 2603.1461
B7: Selling, general & administrative | D7: 850 | E7: 870 | F7: 900 | G7: =G19*G4 -> 930.65764 | H7: =H19*H4 -> 974.29811 | I7: =I19*I4 -> 1019.985 | J7: =J19*J4 -> 1067.8142 | K7: =K19*K4 -> 1117.8862
B8: R&D | D8: 400 | E8: 420 | F8: 400 | G8: =G20*G4 -> 433.75154 | H8: =H20*H4 -> 454.09105 | I8: =I20*I4 -> 475.38433 | J8: =J20*J4 -> 497.67609 | K8: =K20*K4 -> 521.01315
B9: Operating Income | D9: 615 | E9: 795 | F9: 859 | G9: =G6-G7-G8 -> 802.75037 | H9: =H6-H7-H8 -> 840.393 | I9: =I6-I7-I8 -> 879.80078 | J9: =J6-J7-J8 -> 921.05646 | K9: =K6-K7-K8 -> 964.24672
B10: Other Income/(expense), net | D10: 50 | E10: 50 | F10: 50 | G10: =G21 -> 50 | H10: =H21 -> 50 | I10: =I21 -> 50 | J10: =J21 -> 50 | K10: =K21 -> 50
B11: Pre-tax Income | D11: 565 | E11: 745 | F11: 809 | G11: =G9-G10 -> 752.75037 | H11: =H9-H10 -> 790.393 | I11: =I9-I10 -> 829.80078 | J11: =J9-J10 -> 871.05646 | K11: =K9-K10 -> 914.24672
B12: Taxes | D12: 227.5 | E12: 186.25 | F12: 147.25 | G12: =G11*G22 -> 188.18759 | H12: =H11*H22 -> 197.59825 | I12: =I11*I22 -> 207.45019 | J12: =J11*J22 -> 217.76412 | K12: =K11*K22 -> 228.56168
B13: Net Income | D13: 337.5 | E13: 558.75 | F13: 661.75 | G13: =G11-G12 -> 564.56278 | H13: =H11-H12 -> 592.79475 | I13: =I11-I12 -> 622.35058 | J13: =J11-J12 -> 653.29235 | K13: =K11-K12 -> 685.68504
B16: Income Statement Assumptions
B17: Revenue Growth Rate | E17: =(E4-D4)/D4 -> 0.04318618 | F17: =(F4-E4)/E4 -> 0.050597976 | G17: =CHOOSE(Cover!$C$6,Forecast!G26,Forecast!G27,Forecast!G28) -> 0.016892078 | H17: =CHOOSE(Cover!$C$6,Forecast!H26,Forecast!H27,Forecast!H28) -> 0.016892078 | I17: =CHOOSE(Cover!$C$6,Forecast!I26,Forecast!I27,Forecast!I28) -> 0.016892078 | J17: =CHOOSE(Cover!$C$6,Forecast!J26,Forecast!J27,Forecast!J28) -> 0.016892078 | K17: =CHOOSE(Cover!$C$6,Forecast!K26,Forecast!K27,Forecast!K28) -> 0.016892078
B18: COGS as % of Revenue | D18: =D5/D4 -> 0.64203455 | E18: =E5/E4 -> 0.61637534 | F18: =F5/F4 -> 0.62189142 | G18: =AVERAGE(D18:F18) -> 0.6267671 | H18: =G18 -> 0.6267671 | I18: =H18 -> 0.6267671 | J18: =I18 -> 0.6267671 | K18: =J18 -> 0.6267671
B19: SG&A as % of Revenue | D19: =D7/D4 -> 0.16314779 | E19: =E7/E4 -> 0.1600736 | F19: =F7/F4 -> 0.15761821 | G19: =AVERAGE(D19:F19) -> 0.16027987 | H19: =G19 -> 0.16027987 | I19: =H19 -> 0.16027987 | J19: =I19 -> 0.16027987 | K19: =J19 -> 0.16027987
B20: R&D as % of Revenue | D20: =D8/D4 -> 0.076775432 | E20: =E8/E4 -> 0.077276909 | F20: =F8/F4 -> 0.070052539 | G20: =AVERAGE(D20:F20) -> 0.074701627 | H20: =G20 -> 0.074701627 | I20: =H20 -> 0.074701627 | J20: =I20 -> 0.074701627 | K20: =J20 -> 0.074701627
B21: Other income/(expense), net | D21: =D10 -> 50 | E21: =E10 -> 50 | F21: =F10 -> 50 | G21: =F21 -> 50 | H21: =G21 -> 50 | I21: =H21 -> 50 | J21: =I21 -> 50 | K21: =J21 -> 50
B22: Tax Rate | D22: 0.25 | E22: =D22 -> 0.25 | F22: =E22 -> 0.25 | G22: =F22 -> 0.25 | H22: =G22 -> 0.25 | I22: =H22 -> 0.25 | J22: =I22 -> 0.25 | K22: =J22 -> 0.25
B25: Revenue Scenarios
B26: Best Case | G26: =G27+3% -> 0.076892078 | H26: =H27+3% -> 0.076892078 | I26: =I27+3% -> 0.076892078 | J26: =J27+3% -> 0.076892078 | K26: =K27+3% -> 0.076892078
B27: Base Case | G27: =AVERAGE(F17,E17) -> 0.046892078 | H27: =G27 -> 0.046892078 | I27: =H27 -> 0.046892078 | J27: =I27 -> 0.046892078 | K27: =J27 -> 0.046892078
B28: Worst Case | G28: =G27-3% -> 0.016892078 | H28: =H27-3% -> 0.016892078 | I28: =I27-3% -> 0.016892078 | J28: =J27-3% -> 0.016892078 | K28: =K27-3% -> 0.016892078

Sheet Cover
B2: =F6&" Financial Model" -> FinPractice Financial Model
B4: Scenario Analysis | E4: General Settings | H4: Table of Contents
B6: Live Scenario | C6: 3 | E6: Company Name | F6: FinPractice | H6: Cover Page
E7: Company Ticker | F7: ABC | H7: Income Statement
B8: Alerts | E8: Currency | F8: USD | H8: BalanceSheet
E9: Last Update | F9: 46023 | H9: Cash Flow Statement
B10: Balance Sheet Balances? | E10: Contact | F10: Stuart | H10: Assumptions & Drivers
